setup.py
recast_rest_api.egg-info/PKG-INFO
recast_rest_api.egg-info/SOURCES.txt
recast_rest_api.egg-info/dependency_links.txt
recast_rest_api.egg-info/entry_points.txt
recast_rest_api.egg-info/requires.txt
recast_rest_api.egg-info/top_level.txt
recastrestapi/__init__.py
recastrestapi/admincli.py
recastrestapi/apicli.py
recastrestapi/apiconfig.py
recastrestapi/eveconfig.py
recastrestapi/newsettings.py
recastrestapi/server.py
recastrestapi/settings.py
tests/__init__.py
tests/test.py