Metadata-Version: 1.0
Name: recast-rest-api
Version: 0.1.0
Summary: API for the RECAST project
Home-page: https://github.com/cbora/recast-rest-api
Author: Lukas Heinrich, Christian Bora
Author-email: lukas.heinrich@cern.ch, borachristian@gmail.com
License: UNKNOWN
Platform: UNKNOWN
